<?xml version="1.0" encoding="UTF-8"?>
<!DOCTYPE DjVuXML>
<DjVuXML>
<BODY>
<OBJECT data="file://localhost//tmp/derive/lifeadventureinj00clariala//lifeadventureinj00clariala.djvu" height="2294" type="image/x.djvu" usemap="lifeadventureinj00clariala_0002.djvu" width="1478">
<PARAM name="PAGE" value="lifeadventureinj00clariala_0002.djvu"/>
<PARAM name="DPI" value="400"/>
<HIDDENTEXT>
<PAGECOLUMN></PAGECOLUMN>
<PAGECOLUMN>
<REGION>
<PARAGRAPH>
<LINE>
<WORD coords="430,920,602,854">THE</WORD>
<WORD coords="628,918,986,852">LIBRARY</WORD>
</LINE>
</PARAGRAPH>
<PARAGRAPH>
<LINE>
<WORD coords="654,1018,764,954">OF</WORD>
</LINE>
</PARAGRAPH>
<PARAGRAPH>
<LINE>
<WORD coords="348,1116,520,1052">THE</WORD>
<WORD coords="548,1116,1066,1052">UNIVERSITY</WORD>
</LINE>
<LINE>
<WORD coords="376,1214,486,1152">OF</WORD>
<WORD coords="518,1214,1040,1148">CALIFORNIA</WORD>
</LINE>
</PARAGRAPH>
<PARAGRAPH>
<LINE>
<WORD coords="420,1314,578,1250">LOS</WORD>
<WORD coords="604,1314,992,1248">ANGELES</WORD>
</LINE>
</PARAGRAPH>
</REGION>
</PAGECOLUMN>
</HIDDENTEXT>
</OBJECT>
</BODY>
</DjVuXML>
